LICENSE.txt
README.txt
setup.py
GEngine/__init__.py
GEngine/functions.py
GREngine.egg-info/PKG-INFO
GREngine.egg-info/SOURCES.txt
GREngine.egg-info/dependency_links.txt
GREngine.egg-info/top_level.txt