Metadata-Version: 2.1
Name: GREngine
Version: 0.1
Summary: This is for GameEngine
Home-page: UNKNOWN
Author: Ridit Jangra
Author-email: riyanjangra9@gmail.com
License: MIT
Keywords: gameengine
Platform: UNKNOWN
License-File: LICENSE.txt
